cfgone/__init__.py
cfgone/core.py
cfgone-0.1.0.dist-info/METADATA
cfgone-0.1.0.dist-info/WHEEL
cfgone-0.1.0.dist-info/top_level.txt
cfgone-0.1.0.dist-info/RECORD
