Metadata-Version: 2.4
Name: cfgone
Version: 0.1.0
Summary: Load you config with one line of code
Requires-Python: >=3.7
Requires-Dist: pyyaml>=3.10
